pybeaut/__init__.py
pybeaut/test_pybeaut.py
pybeaut-1.1.4.dist-info/METADATA
pybeaut-1.1.4.dist-info/WHEEL
pybeaut-1.1.4.dist-info/licenses/LICENSE
pybeaut-1.1.4.dist-info/RECORD
