Metadata-Version: 2.4
Name: pybeaut
Version: 1.1.4
Summary: A python library for styling terminal outputs.
Project-URL: Author repository, https://github.com/Backist/
Project-URL: repository, https://github.com/Backist/pybeaut
Project-URL: Bug issues, https://github.com/Backist/pybeaut/issues
Author-email: Backest <alvarodrumer54@gmail.com>
Maintainer-email: Backest <alvarodrumer54@gmail.com>, TheWisker <thewisker@protonmail.com>
License-File: LICENSE
Keywords: Miscellaneous tools,Pystyle,Python,Python pretty-prints,Python-stylize,Python-tools,Python3,Python3 tools,Python3-stylize
Classifier: Development Status :: 4 - Beta
Classifier: Environment :: Console
Classifier: License :: OSI Approved :: GNU General Public License v3 or later (GPLv3+)
Classifier: Operating System :: Microsoft :: Windows :: Windows 10
Classifier: Programming Language :: Python :: 3.7
Classifier: Programming Language :: Python :: 3.8
Classifier: Programming Language :: Python :: 3.9
Classifier: Programming Language :: Python :: 3.10
Classifier: Programming Language :: Python :: 3.11
Classifier: Typing :: Typed
Requires-Python: >=3.6
